notion_log_exec/__init__.py
notion_log_exec/__main__.py
notion_log_exec-0.2.4.dist-info/METADATA
notion_log_exec-0.2.4.dist-info/WHEEL
notion_log_exec-0.2.4.dist-info/entry_points.txt
notion_log_exec-0.2.4.dist-info/top_level.txt
notion_log_exec-0.2.4.dist-info/RECORD
