Metadata-Version: 2.1
Name: notion-log-exec
Version: 0.2.4
Summary: Runs a command and reports the result back to a notion collection
Home-page: https://github.com/adjective-object/notion-log-exec
Author: Maxwell Huang-Hobbs
Author-email: mhuan13+pypy@gmail.com
License: UNKNOWN
Platform: UNKNOWN
Classifier: Programming Language :: Python :: 3
Classifier: License :: OSI Approved :: MIT License
Classifier: Operating System :: OS Independent
Requires-Python: >=3.7
Requires-Dist: notion
